[
  {
    "id": "1",
    "name_en": "Mingles",
    "name": "밍글스",
    "category_en": "Korean Contemporary",
    "address": "2F, 19 Dosan-daero 67-gil, Gangnam-gu, Seoul",
    "district_en": "Gangnam",
    "cuisine": "Korean",
    "meal_times": ["Lunch", "Dinner"],
    "description_en": "Mingles offers contemporary Korean cuisine that harmonizes traditional flavors with modern techniques.",
    "lat": 37.5248,
    "lng": 127.0421
  },
  {
    "id": "2",
    "name_en": "Kwon Sook Soo",
    "name": "권숙수",
    "category_en": "Korean Fine Dining",
    "address": "4F, 27 Dosan-daero 81-gil, Gangnam-gu, Seoul",
    "district_en": "Gangnam",
    "cuisine": "Korean",
    "meal_times": ["Lunch", "Dinner"],
    "description_en": "A fine dining restaurant that reinterprets traditional Korean food with seasonal ingredients.",
    "lat": 37.5268,
    "lng": 127.0441
  },
  {
    "id": "3",
    "name_en": "Jungsik",
    "name": "정식당",
    "category_en": "New Korean",
    "address": "11 Seolleung-ro 158-gil, Gangnam-gu, Seoul",
    "district_en": "Gangnam",
    "cuisine": "Korean",
    "meal_times": ["Lunch", "Dinner"],
    "description_en": "Jungsik is a pioneer of modern Korean fine dining, blending Korean ingredients with Western techniques.",
    "lat": 37.5255,
    "lng": 127.0405
  },
  {
    "id": "4",
    "name_en": "La Yeon",
    "name": "라연",
    "category_en": "Korean Traditional",
    "address": "23F, The Shilla Seoul, 249 Dongho-ro, Jung-gu, Seoul",
    "district_en": "Jung-gu",
    "cuisine": "Korean",
    "meal_times": ["Lunch", "Dinner"],
    "description_en": "Elegant Korean fine dining located in The Shilla Seoul, focusing on classic royal cuisine.",
    "lat": 37.5558,
    "lng": 127.0051
  },
  {
    "id": "5",
    "name_en": "Soigne",
    "name": "스와니예",
    "category_en": "Contemporary",
    "address": "B1, 39 Banpo-daero 39-gil, Seocho-gu, Seoul",
    "district_en": "Seocho",
    "cuisine": "Contemporary",
    "meal_times": ["Lunch", "Dinner"],
    "description_en": "Soigne features an 'episodic' menu that changes themes regularly, offering a unique culinary journey.",
    "lat": 37.4942,
    "lng": 127.0065
  },
  {
    "id": "6",
    "name_en": "Gaon",
    "name": "가온",
    "category_en": "Korean Traditional",
    "address": "M Floor, 317 Dosan-daero, Gangnam-gu, Seoul",
    "district_en": "Gangnam",
    "cuisine": "Korean",
    "meal_times": ["Lunch", "Dinner"],
    "description_en": "Gaon focuses on the essence of Korean flavor through traditional recipes and premium ingredients.",
    "lat": 37.5225,
    "lng": 127.0375
  },
  {
    "id": "7",
    "name_en": "Bicena",
    "name": "비채나",
    "category_en": "Korean Fine Dining",
    "address": "81F, Lotte World Tower, 300 Olympic-ro, Songpa-gu, Seoul",
    "district_en": "Songpa",
    "cuisine": "Korean",
    "meal_times": ["Lunch", "Dinner"],
    "description_en": "Located high in the Lotte World Tower, Bicena offers refined Korean dishes with a stunning view.",
    "lat": 37.5126,
    "lng": 127.1025
  },
  {
    "id": "8",
    "name_en": "Mosu",
    "name": "모수",
    "category_en": "Innovative",
    "address": "45 Itaewon-ro 55-gil, Yongsan-gu, Seoul",
    "district_en": "Yongsan",
    "cuisine": "Contemporary",
    "meal_times": ["Lunch", "Dinner"],
    "description_en": "Mosu Seoul, led by Chef Sung Anh, offers a highly innovative and technical dining experience.",
    "lat": 37.5385,
    "lng": 126.9995
  },
  {
    "id": "9",
    "name_en": "Onjium",
    "name": "온지음",
    "category_en": "Korean Heritage",
    "address": "4F, 33 Hyoja-ro, Jongno-gu, Seoul",
    "district_en": "Jongno",
    "cuisine": "Korean",
    "meal_times": ["Lunch", "Dinner"],
    "description_en": "A culinary research institute and restaurant dedicated to preserving and evolving Korean food heritage.",
    "lat": 37.5805,
    "lng": 126.9725
  },
  {
    "id": "10",
    "name_en": "Toc Toc",
    "name": "톡톡",
    "category_en": "French Contemporary",
    "address": "3F, 33 Dosan-daero 81-gil, Gangnam-gu, Seoul",
    "district_en": "Gangnam",
    "cuisine": "French",
    "meal_times": ["Lunch", "Dinner"],
    "description_en": "Toc Toc serves modern French-influenced cuisine with a focus on high-quality seasonal ingredients.",
    "lat": 37.5265,
    "lng": 127.0435
  }
]
