[
  {
    "id": "1",
    "name_en": "Mingles",
    "name": "밍글스",
    "category_en": "Korean Contemporary",
    "address": "2F, 19 Dosan-daero 67-gil, Gangnam-gu",
    "district_en": "Gangnam",
    "cuisine": "Korean",
    "meal_times": [
      "Lunch",
      "Dinner"
    ],
    "description_en": "Contemporary Korean cuisine harmonizing traditional flavors with modern techniques.",
    "lat": 37.5248,
    "lng": 127.0421,
    "ribbons": 3,
    "michelin": "3 Stars"
  },
  {
    "id": "2",
    "name_en": "Kwon Sook Soo",
    "name": "권숙수",
    "category_en": "Korean Fine Dining",
    "address": "4F, 27 Dosan-daero 81-gil, Gangnam-gu",
    "district_en": "Gangnam",
    "cuisine": "Korean",
    "meal_times": [
      "Lunch",
      "Dinner"
    ],
    "description_en": "Fine dining reinterpreting traditional Korean food with seasonal ingredients.",
    "lat": 37.5268,
    "lng": 127.0441,
    "ribbons": 3,
    "michelin": "2 Stars"
  },
  {
    "id": "3",
    "name_en": "Jungsik",
    "name": "정식당",
    "category_en": "New Korean",
    "address": "11 Seolleung-ro 158-gil, Gangnam-gu",
    "district_en": "Gangnam",
    "cuisine": "Korean",
    "meal_times": [
      "Lunch",
      "Dinner"
    ],
    "description_en": "Pioneer of modern Korean fine dining, blending Korean ingredients with Western techniques.",
    "lat": 37.5255,
    "lng": 127.0405,
    "ribbons": 3,
    "michelin": "2 Stars"
  },
  {
    "id": "4",
    "name_en": "La Yeon",
    "name": "라연",
    "category_en": "Korean Traditional",
    "address": "23F, The Shilla Seoul, 249 Dongho-ro, Jung-gu",
    "district_en": "Jung-gu",
    "cuisine": "Korean",
    "meal_times": [
      "Lunch",
      "Dinner"
    ],
    "description_en": "Elegant Korean fine dining located in The Shilla Seoul, focusing on classic royal cuisine.",
    "lat": 37.5558,
    "lng": 127.0051,
    "michelin": "2 Stars"
  },
  {
    "id": "5",
    "name_en": "Soigne",
    "name": "스와니예",
    "category_en": "Contemporary",
    "address": "B1, 39 Banpo-daero 39-gil, Seocho-gu",
    "district_en": "Seocho",
    "cuisine": "Contemporary",
    "meal_times": [
      "Lunch",
      "Dinner"
    ],
    "description_en": "Features an 'episodic' menu that changes themes regularly, offering a unique culinary journey.",
    "lat": 37.4942,
    "lng": 127.0065,
    "ribbons": 3,
    "michelin": "2 Stars"
  },
  {
    "id": "6",
    "name_en": "Gaon",
    "name": "가온",
    "category_en": "Korean Traditional",
    "address": "M Floor, 317 Dosan-daero, Gangnam-gu",
    "district_en": "Gangnam",
    "cuisine": "Korean",
    "meal_times": [
      "Lunch",
      "Dinner"
    ],
    "description_en": "Focuses on the essence of Korean flavor through traditional recipes and premium ingredients.",
    "lat": 37.5225,
    "lng": 127.0375
  },
  {
    "id": "7",
    "name_en": "Bicena",
    "name": "비채나",
    "category_en": "Korean Fine Dining",
    "address": "81F, Lotte World Tower, 300 Olympic-ro, Songpa-gu",
    "district_en": "Songpa",
    "cuisine": "Korean",
    "meal_times": [
      "Lunch",
      "Dinner"
    ],
    "description_en": "Located high in the Lotte World Tower, offering refined Korean dishes with a stunning view.",
    "lat": 37.5126,
    "lng": 127.1025,
    "michelin": "1 Star"
  },
  {
    "id": "8",
    "name_en": "Mosu",
    "name": "모수",
    "category_en": "Innovative",
    "address": "45 Itaewon-ro 55-gil, Yongsan-gu",
    "district_en": "Yongsan",
    "cuisine": "Contemporary",
    "meal_times": [
      "Lunch",
      "Dinner"
    ],
    "description_en": "Led by Chef Sung Anh, offers a highly innovative and technical dining experience.",
    "lat": 37.5385,
    "lng": 126.9995,
    "ribbons": 3,
    "michelin": "3 Stars",
    "ccw_chef": "Ahn Sung-jae"
  },
  {
    "id": "9",
    "name_en": "Onjium",
    "name": "온지음",
    "category_en": "Korean Heritage",
    "address": "4F, 33 Hyoja-ro, Jongno-gu",
    "district_en": "Jongno",
    "cuisine": "Korean",
    "meal_times": [
      "Lunch",
      "Dinner"
    ],
    "description_en": "Culinary research institute and restaurant dedicated to preserving and evolving Korean food heritage.",
    "lat": 37.5805,
    "lng": 126.9725,
    "ribbons": 3,
    "michelin": "2 Stars"
  },
  {
    "id": "10",
    "name_en": "Toc Toc",
    "name": "톡톡",
    "category_en": "French Contemporary",
    "address": "3F, 33 Dosan-daero 81-gil, Gangnam-gu",
    "district_en": "Gangnam",
    "cuisine": "French",
    "meal_times": [
      "Lunch",
      "Dinner"
    ],
    "description_en": "Modern French-influenced cuisine with a focus on high-quality seasonal ingredients.",
    "lat": 37.5265,
    "lng": 127.0435
  },
  {
    "id": "11",
    "name_en": "Zero Complex",
    "name": "제로 컴플렉스",
    "category_en": "French Contemporary",
    "address": "4F, 19-7 Toegye-ro 2-ga, Jung-gu",
    "district_en": "Jung-gu",
    "cuisine": "French",
    "meal_times": [
      "Lunch",
      "Dinner"
    ],
    "description_en": "Innovative French cuisine with a focus on natural wines and creative pairings.",
    "lat": 37.5585,
    "lng": 126.9855,
    "ribbons": 3,
    "michelin": "1 Star"
  },
  {
    "id": "12",
    "name_en": "Pierre Gagnaire",
    "name": "피에르 가니에르",
    "category_en": "French Fine Dining",
    "address": "35F, Lotte Hotel Seoul, 30 Eulji-ro, Jung-gu",
    "district_en": "Jung-gu",
    "cuisine": "French",
    "meal_times": [
      "Lunch",
      "Dinner"
    ],
    "description_en": "The Seoul outpost of the legendary French chef, offering artistic and complex dishes.",
    "lat": 37.5652,
    "lng": 126.9812
  },
  {
    "id": "13",
    "name_en": "Ryunique",
    "name": "류니끄",
    "category_en": "Innovative",
    "address": "40 Gangnam-daero 162-gil, Gangnam-gu",
    "district_en": "Gangnam",
    "cuisine": "Innovative",
    "meal_times": [
      "Lunch",
      "Dinner"
    ],
    "description_en": "Chef Tae-hwan Ryu's signature 'Hybrid Cuisine' blending Japanese and French techniques.",
    "lat": 37.5212,
    "lng": 127.0225
  },
  {
    "id": "14",
    "name_en": "L'Amitié",
    "name": "라미띠에",
    "category_en": "French Traditional",
    "address": "2F, 7 Eonju-ro 153-gil, Gangnam-gu",
    "district_en": "Gangnam",
    "cuisine": "French",
    "meal_times": [
      "Lunch",
      "Dinner"
    ],
    "description_en": "One of the oldest French restaurants in Seoul, serving classic and refined French fare.",
    "lat": 37.5235,
    "lng": 127.0355
  },
  {
    "id": "15",
    "name_en": "Dining in Space",
    "name": "다이닝 인 스페이스",
    "category_en": "French Contemporary",
    "address": "5F, 83 Yulgok-ro, Jongno-gu",
    "district_en": "Jongno",
    "cuisine": "French",
    "meal_times": [
      "Lunch",
      "Dinner"
    ],
    "description_en": "Modern French dining with a spectacular view of the Arario Museum and Changdeokgung Palace.",
    "lat": 37.5762,
    "lng": 126.9905
  },
  {
    "id": "16",
    "name_en": "Kojima",
    "name": "코지마",
    "category_en": "Sushi",
    "address": "6F, 442 Dosan-daero, Gangnam-gu",
    "district_en": "Gangnam",
    "cuisine": "Japanese",
    "meal_times": [
      "Lunch",
      "Dinner"
    ],
    "description_en": "Top-tier sushi omakase experience focusing on the purest flavors of the sea.",
    "lat": 37.5238,
    "lng": 127.0415,
    "michelin": "2 Stars"
  },
  {
    "id": "17",
    "name_en": "Sushi Hyo",
    "name": "스시효",
    "category_en": "Sushi",
    "address": "21 Seolleung-ro 146-gil, Gangnam-gu",
    "district_en": "Gangnam",
    "cuisine": "Japanese",
    "meal_times": [
      "Lunch",
      "Dinner"
    ],
    "description_en": "Classic sushi omakase by Chef Hyo-ki Ahn, a pioneer of the high-end sushi scene in Seoul.",
    "lat": 37.5228,
    "lng": 127.0402
  },
  {
    "id": "18",
    "name_en": "Mokmyeok Sanbang",
    "name": "목멱산방",
    "category_en": "Bibimbap",
    "address": "71 Toegye-ro 20-gil, Jung-gu",
    "district_en": "Jung-gu",
    "cuisine": "Korean",
    "meal_times": [
      "Lunch",
      "Dinner"
    ],
    "description_en": "Famous for its authentic and healthy bibimbap served on the slopes of Namsan Mountain.",
    "lat": 37.5562,
    "lng": 126.9845
  },
  {
    "id": "19",
    "name_en": "Woo Lae Oak",
    "name": "우래옥",
    "category_en": "Pyongyang Naengmyeon",
    "address": "62-11 Changgyeonggung-ro, Jung-gu",
    "district_en": "Jung-gu",
    "cuisine": "Korean",
    "meal_times": [
      "Lunch",
      "Dinner"
    ],
    "description_en": "A legendary institution serving some of the best Pyongyang-style cold buckwheat noodles in Seoul.",
    "lat": 37.5682,
    "lng": 126.9992
  },
  {
    "id": "20",
    "name_en": "Jin Jin",
    "name": "진진",
    "category_en": "Chinese",
    "address": "60 World Cup-buk-ro 1-gil, Mapo-gu",
    "district_en": "Mapo",
    "cuisine": "Chinese",
    "meal_times": [
      "Dinner"
    ],
    "description_en": "Celebrated for its authentic Chinese cuisine and signature dishes like Menbosha.",
    "lat": 37.5542,
    "lng": 126.9125,
    "ccw_chef": "Hwang Jin-seon"
  },
  {
    "id": "21",
    "name_en": "Pildong Myeonok",
    "name": "필동면옥",
    "category_en": "Pyongyang Naengmyeon",
    "address": "26 Seoae-ro, Jung-gu",
    "district_en": "Jung-gu",
    "cuisine": "Korean",
    "meal_times": [
      "Lunch",
      "Dinner"
    ],
    "description_en": "Known for its delicate and clean-tasting Pyongyang naengmyeon broth.",
    "lat": 37.5605,
    "lng": 126.9962
  },
  {
    "id": "22",
    "name_en": "Eulji Myeonok",
    "name": "을지면옥",
    "category_en": "Pyongyang Naengmyeon",
    "address": "2-1 Eulji-ro 3-ga, Jung-gu",
    "district_en": "Jung-gu",
    "cuisine": "Korean",
    "meal_times": [
      "Lunch",
      "Dinner"
    ],
    "description_en": "Another staple of the Seoul naengmyeon scene, beloved for its thin noodles and savory broth.",
    "lat": 37.5668,
    "lng": 126.9925
  },
  {
    "id": "23",
    "name_en": "Myeongdong Kyoja",
    "name": "명동교자",
    "category_en": "Kalguksu",
    "address": "29 Myeongdong 10-gil, Jung-gu",
    "district_en": "Jung-gu",
    "cuisine": "Korean",
    "meal_times": [
      "Lunch",
      "Dinner"
    ],
    "description_en": "Famous for its handmade kalguksu (knife-cut noodles) and intensely garlic-heavy kimchi.",
    "lat": 37.5625,
    "lng": 126.9855
  },
  {
    "id": "24",
    "name_en": "Tosokchon Samgyetang",
    "name": "토속촌 삼계탕",
    "category_en": "Samgyetang",
    "address": "5 Jahamun-ro 5-gil, Jongno-gu",
    "district_en": "Jongno",
    "cuisine": "Korean",
    "meal_times": [
      "Lunch",
      "Dinner"
    ],
    "description_en": "The most famous spot for samgyetang (ginseng chicken soup), once a favorite of former presidents.",
    "lat": 37.5775,
    "lng": 126.9725
  },
  {
    "id": "25",
    "name_en": "Goryeo Samgyetang",
    "name": "고려삼계탕",
    "category_en": "Samgyetang",
    "address": "55-3 Seosomun-ro, Jung-gu",
    "district_en": "Jung-gu",
    "cuisine": "Korean",
    "meal_times": [
      "Lunch",
      "Dinner"
    ],
    "description_en": "The first samgyetang restaurant in Seoul, serving healthy and hearty chicken soup since 1960.",
    "lat": 37.5635,
    "lng": 126.9745
  },
  {
    "id": "26",
    "name_en": "Imun Seolnongtang",
    "name": "이문 설농탕",
    "category_en": "Seolleongtang",
    "address": "38-13 Ujeongguk-ro, Jongno-gu",
    "district_en": "Jongno",
    "cuisine": "Korean",
    "meal_times": [
      "Breakfast",
      "Lunch",
      "Dinner"
    ],
    "description_en": "The oldest restaurant in Korea, serving rich and milky ox bone soup for over a century.",
    "lat": 37.5735,
    "lng": 126.9835
  },
  {
    "id": "27",
    "name_en": "Hadongkwan",
    "name": "하동관",
    "category_en": "Gomtang",
    "address": "12 Myeongdong 9-gil, Jung-gu",
    "district_en": "Jung-gu",
    "cuisine": "Korean",
    "meal_times": [
      "Breakfast",
      "Lunch"
    ],
    "description_en": "A legendary gomtang (beef bone soup) house that has been a favorite for generations.",
    "lat": 37.5645,
    "lng": 126.9848
  },
  {
    "id": "28",
    "name_en": "Okdongshik",
    "name": "옥동식",
    "category_en": "Dwaeji-gomtang",
    "address": "44-10 Yanghwa-ro 7-gil, Mapo-gu",
    "district_en": "Mapo",
    "cuisine": "Korean",
    "meal_times": [
      "Lunch",
      "Dinner"
    ],
    "description_en": "Renowned for its clear and refined pork bone soup, a modern take on a classic comfort food.",
    "lat": 37.5515,
    "lng": 126.9155
  },
  {
    "id": "29",
    "name_en": "Hanchu",
    "name": "한추",
    "category_en": "Korean Fried Chicken",
    "address": "68 Nonhyeon-ro 175-gil, Gangnam-gu",
    "district_en": "Gangnam",
    "cuisine": "Korean",
    "meal_times": [
      "Dinner"
    ],
    "description_en": "Famous for its spicy fried chicken and fried green peppers, a staple of the Garosu-gil scene.",
    "lat": 37.5245,
    "lng": 127.0245
  },
  {
    "id": "30",
    "name_en": "Kyochon Chicken",
    "name": "교촌치킨",
    "category_en": "Korean Fried Chicken",
    "address": "372 Jong-ro, Jongno-gu",
    "district_en": "Jongno",
    "cuisine": "Korean",
    "meal_times": [
      "Lunch",
      "Dinner"
    ],
    "description_en": "One of Korea's most famous chicken chains, known for its honey and soy garlic sauces.",
    "lat": 37.5705,
    "lng": 127.0085
  },
  {
    "id": "31",
    "name_en": "Jinmi Pyeongyang Naengmyeon",
    "name": "진미평양냉면",
    "category_en": "Pyongyang Naengmyeon",
    "address": "115-10 Hakdong-ro, Gangnam-gu",
    "district_en": "Gangnam",
    "cuisine": "Korean",
    "meal_times": [
      "Lunch",
      "Dinner"
    ],
    "description_en": "Renowned for its clean and savory cold buckwheat noodles, a local favorite in Gangnam.",
    "lat": 37.5132,
    "lng": 127.0345,
    "michelin": "Bib Gourmand"
  },
  {
    "id": "32",
    "name_en": "Woo Rae Oak",
    "name": "우래옥",
    "category_en": "Pyongyang Naengmyeon",
    "address": "62-11 Changgyeonggung-ro, Jung-gu",
    "district_en": "Jung-gu",
    "cuisine": "Korean",
    "meal_times": [
      "Lunch",
      "Dinner"
    ],
    "description_en": "One of Seoul's most historic restaurants, famous for its deep-flavored beef broth naengmyeon.",
    "lat": 37.5682,
    "lng": 126.9992,
    "michelin": "Bib Gourmand"
  },
  {
    "id": "34",
    "name_en": "Ojang-dong Heungnam-jip",
    "name": "오장동흥남집",
    "category_en": "Hamhung Naengmyeon",
    "address": "114 Mareunnae-ro, Jung-gu",
    "district_en": "Jung-gu",
    "cuisine": "Korean",
    "meal_times": [
      "Lunch",
      "Dinner"
    ],
    "description_en": "Famous for its spicy Hamhung-style cold noodles since 1953.",
    "lat": 37.5638,
    "lng": 127.0025,
    "michelin": "Bib Gourmand"
  },
  {
    "id": "35",
    "name_en": "Tuk Tuk Isan",
    "name": "툭툭누들타이",
    "category_en": "Thai",
    "address": "161-8 Seongmisan-ro, Mapo-gu",
    "district_en": "Mapo",
    "cuisine": "Thai",
    "meal_times": [
      "Lunch",
      "Dinner"
    ],
    "description_en": "Vibrant and authentic Thai flavors in the heart of Yeonnam-dong.",
    "lat": 37.5615,
    "lng": 126.9245,
    "michelin": "Bib Gourmand"
  },
  {
    "id": "36",
    "name_en": "Soseoul Hannam",
    "name": "소서울 한남",
    "category_en": "Korean Contemporary",
    "address": "31-18 Hannam-daero 20-gil, Yongsan-gu",
    "district_en": "Yongsan",
    "cuisine": "Korean",
    "meal_times": [
      "Lunch",
      "Dinner"
    ],
    "description_en": "Refined Korean contemporary cuisine with a focus on seasonal storytelling.",
    "lat": 37.5355,
    "lng": 127.0085,
    "michelin": "1 Star"
  },
  {
    "id": "37",
    "name_en": "Giga",
    "name": "기가스",
    "category_en": "Mediterranean",
    "address": "2F, 48 Dosan-daero 45-gil, Gangnam-gu",
    "district_en": "Gangnam",
    "cuisine": "Mediterranean",
    "meal_times": [
      "Lunch",
      "Dinner"
    ],
    "description_en": "Farm-to-table Mediterranean cuisine focusing on the essence of ingredients.",
    "lat": 37.5235,
    "lng": 127.0385,
    "michelin": "1 Star"
  },
  {
    "id": "38",
    "name_en": "Escondido",
    "name": "에스콘디도",
    "category_en": "Mexican",
    "address": "B1, 10-11 Hannam-daero 20-gil, Yongsan-gu",
    "district_en": "Yongsan",
    "cuisine": "Mexican",
    "meal_times": [
      "Dinner"
    ],
    "description_en": "Sophisticated Mexican dining that reinterprets traditional flavors with modern techniques.",
    "lat": 37.5345,
    "lng": 127.0095,
    "michelin": "1 Star"
  },
  {
    "id": "39",
    "name_en": "Soul",
    "name": "소울",
    "category_en": "Korean Contemporary",
    "address": "B1, 26 Sinheung-ro 26-gil, Yongsan-gu",
    "district_en": "Yongsan",
    "cuisine": "Korean",
    "meal_times": [
      "Lunch",
      "Dinner"
    ],
    "description_en": "A creative dining space where Korean flavors meet modern culinary art.",
    "lat": 37.5425,
    "lng": 126.9865,
    "michelin": "1 Star",
    "ccw_chef": "Kim Hee-eun"
  },
  {
    "id": "40",
    "name_en": "Hane",
    "name": "하네",
    "category_en": "Sushi",
    "address": "2F, 26 Eonju-ro 172-gil, Gangnam-gu",
    "district_en": "Gangnam",
    "cuisine": "Japanese",
    "meal_times": [
      "Lunch",
      "Dinner"
    ],
    "description_en": "Exceptional sushi omakase focusing on the purity and seasonal quality of fish.",
    "lat": 37.5265,
    "lng": 127.0375,
    "michelin": "1 Star",
    "ribbons": 3
  },
  {
    "id": "41",
    "name_en": "Eatanic Garden",
    "name": "이타닉 가든",
    "category_en": "Korean Contemporary",
    "address": "36F, Josun Palace, 231 Teheran-ro, Gangnam-gu",
    "district_en": "Gangnam",
    "cuisine": "Korean",
    "meal_times": [
      "Lunch",
      "Dinner"
    ],
    "description_en": "Luxurious dining experience with a panoramic view and artistic Korean dishes.",
    "lat": 37.5025,
    "lng": 127.0415,
    "michelin": "1 Star",
    "ribbons": 3,
    "ccw_chef": "Son Jong-won"
  },
  {
    "id": "42",
    "name_en": "Solbam",
    "name": "솔밤",
    "category_en": "Korean Contemporary",
    "address": "2F, 6 Dosan-daero 37-gil, Gangnam-gu",
    "district_en": "Gangnam",
    "cuisine": "Korean",
    "meal_times": [
      "Dinner"
    ],
    "description_en": "Contemporary Korean cuisine that tells a story of nature and tradition.",
    "lat": 37.5215,
    "lng": 127.0365,
    "michelin": "1 Star",
    "ribbons": 3
  },
  {
    "id": "43",
    "name_en": "7th Door",
    "name": "세븐스도어",
    "category_en": "Korean Contemporary",
    "address": "4F, 41 Hakdong-ro 97-gil, Gangnam-gu",
    "district_en": "Gangnam",
    "cuisine": "Korean",
    "meal_times": [
      "Lunch",
      "Dinner"
    ],
    "description_en": "Chef Kim Dae-chun's exploration of the seven tastes of Korean cuisine.",
    "lat": 37.5245,
    "lng": 127.0495,
    "michelin": "1 Star",
    "ribbons": 3
  },
  {
    "id": "44",
    "name_en": "Muoki",
    "name": "무오키",
    "category_en": "Contemporary",
    "address": "2F, 12-12 Hakdong-ro 55-gil, Gangnam-gu",
    "district_en": "Gangnam",
    "cuisine": "Contemporary",
    "meal_times": [
      "Lunch",
      "Dinner"
    ],
    "description_en": "Innovative cuisine focusing on diverse textures and cooking methods.",
    "lat": 37.5195,
    "lng": 127.0435,
    "michelin": "1 Star",
    "ribbons": 3
  },
  {
    "id": "45",
    "name_en": "L'Amant Secret",
    "name": "라망 시크레",
    "category_en": "Contemporary",
    "address": "26F, L'Escape Hotel, 67 Toegye-ro, Jung-gu",
    "district_en": "Jung-gu",
    "cuisine": "Contemporary",
    "meal_times": [
      "Lunch",
      "Dinner"
    ],
    "description_en": "Whimsical and sophisticated dining with a focus on local ingredients and storytelling.",
    "lat": 37.5595,
    "lng": 126.9795,
    "michelin": "1 Star",
    "ribbons": 3
  },
  {
    "id": "46",
    "name_en": "Mitou",
    "name": "미토우",
    "category_en": "Japanese",
    "address": "2F, 11-5 Eonju-ro 150-gil, Gangnam-gu",
    "district_en": "Gangnam",
    "cuisine": "Japanese",
    "meal_times": [
      "Dinner"
    ],
    "description_en": "Authentic Japanese kaiseki that emphasizes the natural flavors of seasonal ingredients.",
    "lat": 37.5225,
    "lng": 127.0345,
    "michelin": "2 Stars",
    "ribbons": 3
  },
  {
    "id": "48",
    "name_en": "Alla Prima",
    "name": "알라프리마",
    "category_en": "Innovative",
    "address": "2F, 17 Hakdong-ro 17-gil, Gangnam-gu",
    "district_en": "Gangnam",
    "cuisine": "Innovative",
    "meal_times": [
      "Lunch",
      "Dinner"
    ],
    "description_en": "Chef Kim Jin-hyuk's creative and technical approach to global ingredients.",
    "lat": 37.5125,
    "lng": 127.0245,
    "michelin": "2 Stars",
    "ribbons": 3
  },
  {
    "id": "49",
    "name_en": "Joo Ok",
    "name": "주옥",
    "category_en": "Korean Contemporary",
    "address": "2F, The Plaza Seoul, 119 Taepyung-ro 2-ga, Jung-gu",
    "district_en": "Jung-gu",
    "cuisine": "Korean",
    "meal_times": [
      "Lunch",
      "Dinner"
    ],
    "description_en": "Celebrates the beauty of Korean ingredients and traditional fermentation.",
    "lat": 37.5645,
    "lng": 126.9785,
    "michelin": "2 Stars"
  },
  {
    "id": "ccw_s1_w_0",
    "name_en": "Choi Dot",
    "name": "Choi Dot",
    "category_en": "Culinary Class Wars",
    "address": "Gangnam, Seoul",
    "district_en": "Gangnam",
    "cuisine": "Various",
    "meal_times": [
      "Lunch",
      "Dinner"
    ],
    "description_en": "Restaurant of Chef Choi Hyun-seok from Culinary Class Wars Season 1.",
    "lat": 37.5665,
    "lng": 126.978,
    "ccw_chef": "Choi Hyun-seok"
  },
  {
    "id": "ccw_s1_w_1",
    "name_en": "Hong Bo Gak",
    "name": "Hong Bo Gak",
    "category_en": "Culinary Class Wars",
    "address": "Gangnam, Seoul",
    "district_en": "Gangnam",
    "cuisine": "Various",
    "meal_times": [
      "Lunch",
      "Dinner"
    ],
    "description_en": "Restaurant of Chef Lu Chinglai from Culinary Class Wars Season 1.",
    "lat": 37.5665,
    "lng": 126.978,
    "ccw_chef": "Lu Chinglai"
  },
  {
    "id": "ccw_s1_w_2",
    "name_en": "Tian Mi Mi",
    "name": "Tian Mi Mi",
    "category_en": "Culinary Class Wars",
    "address": "Seochon/Gangnam, Seoul",
    "district_en": "Seochon/Gangnam",
    "cuisine": "Various",
    "meal_times": [
      "Lunch",
      "Dinner"
    ],
    "description_en": "Restaurant of Chef Jung Ji-sun from Culinary Class Wars Season 1.",
    "lat": 37.5665,
    "lng": 126.978,
    "ccw_chef": "Jung Ji-sun"
  },
  {
    "id": "ccw_s1_w_3",
    "name_en": "Yun Seoul",
    "name": "Yun Seoul",
    "category_en": "Culinary Class Wars",
    "address": "Gangnam, Seoul",
    "district_en": "Gangnam",
    "cuisine": "Various",
    "meal_times": [
      "Lunch",
      "Dinner"
    ],
    "description_en": "Restaurant of Chef Kim Do-yun from Culinary Class Wars Season 1.",
    "lat": 37.5665,
    "lng": 126.978,
    "ccw_chef": "Kim Do-yun"
  },
  {
    "id": "ccw_s1_w_4",
    "name_en": "Evett",
    "name": "Evett",
    "category_en": "Culinary Class Wars",
    "address": "Gangnam, Seoul",
    "district_en": "Gangnam",
    "cuisine": "Various",
    "meal_times": [
      "Lunch",
      "Dinner"
    ],
    "description_en": "Restaurant of Chef Joseph Lidgerwood from Culinary Class Wars Season 1.",
    "lat": 37.5665,
    "lng": 126.978,
    "ccw_chef": "Joseph Lidgerwood"
  },
  {
    "id": "ccw_s1_w_5",
    "name_en": "Fabri Kitchen",
    "name": "Fabri Kitchen",
    "category_en": "Culinary Class Wars",
    "address": "Yongsan, Seoul",
    "district_en": "Yongsan",
    "cuisine": "Various",
    "meal_times": [
      "Lunch",
      "Dinner"
    ],
    "description_en": "Restaurant of Chef Fabrizio Ferrari from Culinary Class Wars Season 1.",
    "lat": 37.5665,
    "lng": 126.978,
    "ccw_chef": "Fabrizio Ferrari"
  },
  {
    "id": "ccw_s1_w_6",
    "name_en": "Gisdeun",
    "name": "Gisdeun",
    "category_en": "Culinary Class Wars",
    "address": "Gangnam, Seoul",
    "district_en": "Gangnam",
    "cuisine": "Various",
    "meal_times": [
      "Lunch",
      "Dinner"
    ],
    "description_en": "Restaurant of Chef Bang Ki-su from Culinary Class Wars Season 1.",
    "lat": 37.5665,
    "lng": 126.978,
    "ccw_chef": "Bang Ki-su"
  },
  {
    "id": "ccw_s1_w_7",
    "name_en": "Sikdang Neo",
    "name": "Sikdang Neo",
    "category_en": "Culinary Class Wars",
    "address": "Songpa, Seoul",
    "district_en": "Songpa",
    "cuisine": "Various",
    "meal_times": [
      "Lunch",
      "Dinner"
    ],
    "description_en": "Restaurant of Chef Choi Kang-rok from Culinary Class Wars Season 1.",
    "lat": 37.5665,
    "lng": 126.978,
    "ccw_chef": "Choi Kang-rok"
  },
  {
    "id": "ccw_s1_w_8",
    "name_en": "Na Gyeong Mushroom Farm",
    "name": "Na Gyeong Mushroom Farm",
    "category_en": "Culinary Class Wars",
    "address": "Buyeo, Seoul",
    "district_en": "Buyeo",
    "cuisine": "Various",
    "meal_times": [
      "Lunch",
      "Dinner"
    ],
    "description_en": "Restaurant of Chef Lee Young-suk from Culinary Class Wars Season 1.",
    "lat": 37.5665,
    "lng": 126.978,
    "ccw_chef": "Lee Young-suk"
  },
  {
    "id": "ccw_s1_w_9",
    "name_en": "Local EAT",
    "name": "Local EAT",
    "category_en": "Culinary Class Wars",
    "address": "Seongdong, Seoul",
    "district_en": "Seongdong",
    "cuisine": "Various",
    "meal_times": [
      "Lunch",
      "Dinner"
    ],
    "description_en": "Restaurant of Chef Nam Jeong-seok from Culinary Class Wars Season 1.",
    "lat": 37.5665,
    "lng": 126.978,
    "ccw_chef": "Nam Jeong-seok"
  },
  {
    "id": "ccw_s1_b_11",
    "name_en": "Via Toledo Pasta Bar",
    "name": "Via Toledo Pasta Bar",
    "category_en": "Culinary Class Wars",
    "address": "Yongsan, Seoul",
    "district_en": "Yongsan",
    "cuisine": "Various",
    "meal_times": [
      "Lunch",
      "Dinner"
    ],
    "description_en": "Restaurant of Chef Napoli Mafia (Kwon Seong-jun) from Culinary Class Wars Season 1.",
    "lat": 37.5665,
    "lng": 126.978,
    "ccw_chef": "Napoli Mafia (Kwon Seong-jun)"
  },
  {
    "id": "ccw_s1_b_12",
    "name_en": "Deepin",
    "name": "Deepin",
    "category_en": "Culinary Class Wars",
    "address": "Jung-gu/Seongdong, Seoul",
    "district_en": "Jung-gu/Seongdong",
    "cuisine": "Various",
    "meal_times": [
      "Lunch",
      "Dinner"
    ],
    "description_en": "Restaurant of Chef Cooking Maniac (Yoon Nam-no) from Culinary Class Wars Season 1.",
    "lat": 37.5665,
    "lng": 126.978,
    "ccw_chef": "Cooking Maniac (Yoon Nam-no)"
  },
  {
    "id": "ccw_s1_b_13",
    "name_en": "Andongjip Son Kalguksi",
    "name": "Andongjip Son Kalguksi",
    "category_en": "Culinary Class Wars",
    "address": "Dongdaemun, Seoul",
    "district_en": "Dongdaemun",
    "cuisine": "Various",
    "meal_times": [
      "Lunch",
      "Dinner"
    ],
    "description_en": "Restaurant of Chef Auntie Omakase #1 (Kim Mi-ryung) from Culinary Class Wars Season 1.",
    "lat": 37.5665,
    "lng": 126.978,
    "ccw_chef": "Auntie Omakase #1 (Kim Mi-ryung)"
  },
  {
    "id": "ccw_s1_b_14",
    "name_en": "Trid",
    "name": "Trid",
    "category_en": "Culinary Class Wars",
    "address": "Gangnam, Seoul",
    "district_en": "Gangnam",
    "cuisine": "Various",
    "meal_times": [
      "Lunch",
      "Dinner"
    ],
    "description_en": "Restaurant of Chef Triple Star (Kang Seung-won) from Culinary Class Wars Season 1.",
    "lat": 37.5665,
    "lng": 126.978,
    "ccw_chef": "Triple Star (Kang Seung-won)"
  },
  {
    "id": "ccw_s1_b_15",
    "name_en": "Doryang",
    "name": "Doryang",
    "category_en": "Culinary Class Wars",
    "address": "Jongno, Seoul",
    "district_en": "Jongno",
    "cuisine": "Various",
    "meal_times": [
      "Lunch",
      "Dinner"
    ],
    "description_en": "Restaurant of Chef Self-Made Chef (Lim Tae-hoon) from Culinary Class Wars Season 1.",
    "lat": 37.5665,
    "lng": 126.978,
    "ccw_chef": "Self-Made Chef (Lim Tae-hoon)"
  },
  {
    "id": "ccw_s1_b_16",
    "name_en": "Cho Kwang 201",
    "name": "Cho Kwang 201",
    "category_en": "Culinary Class Wars",
    "address": "Songpa, Seoul",
    "district_en": "Songpa",
    "cuisine": "Various",
    "meal_times": [
      "Lunch",
      "Dinner"
    ],
    "description_en": "Restaurant of Chef Comic Book Chef (Cho Kwang-hyo) from Culinary Class Wars Season 1.",
    "lat": 37.5665,
    "lng": 126.978,
    "ccw_chef": "Comic Book Chef (Cho Kwang-hyo)"
  },
  {
    "id": "ccw_s1_b_17",
    "name_en": "Bornyon",
    "name": "Bornyon",
    "category_en": "Culinary Class Wars",
    "address": "Gangnam, Seoul",
    "district_en": "Gangnam",
    "cuisine": "Various",
    "meal_times": [
      "Lunch",
      "Dinner"
    ],
    "description_en": "Restaurant of Chef One-Two-Three (Bae Kyung-jun) from Culinary Class Wars Season 1.",
    "lat": 37.5665,
    "lng": 126.978,
    "ccw_chef": "One-Two-Three (Bae Kyung-jun)"
  },
  {
    "id": "ccw_s1_b_18",
    "name_en": "Namyeong-tak",
    "name": "Namyeong-tak",
    "category_en": "Culinary Class Wars",
    "address": "Yongsan, Seoul",
    "district_en": "Yongsan",
    "cuisine": "Various",
    "meal_times": [
      "Lunch",
      "Dinner"
    ],
    "description_en": "Restaurant of Chef Meat Master from Culinary Class Wars Season 1.",
    "lat": 37.5665,
    "lng": 126.978,
    "ccw_chef": "Meat Master"
  },
  {
    "id": "ccw_s1_b_19",
    "name_en": "Pono Buono",
    "name": "Pono Buono",
    "category_en": "Culinary Class Wars",
    "address": "Gangnam, Seoul",
    "district_en": "Gangnam",
    "cuisine": "Various",
    "meal_times": [
      "Lunch",
      "Dinner"
    ],
    "description_en": "Restaurant of Chef Hidden Genius from Culinary Class Wars Season 1.",
    "lat": 37.5665,
    "lng": 126.978,
    "ccw_chef": "Hidden Genius"
  },
  {
    "id": "ccw_s1_b_20",
    "name_en": "Yakitori Muk",
    "name": "Yakitori Muk",
    "category_en": "Culinary Class Wars",
    "address": "Mapo, Seoul",
    "district_en": "Mapo",
    "cuisine": "Various",
    "meal_times": [
      "Lunch",
      "Dinner"
    ],
    "description_en": "Restaurant of Chef Yakitori King from Culinary Class Wars Season 1.",
    "lat": 37.5665,
    "lng": 126.978,
    "ccw_chef": "Yakitori King"
  },
  {
    "id": "ccw_s2_w_21",
    "name_en": "Hobin",
    "name": "Hobin",
    "category_en": "Culinary Class Wars",
    "address": "Jung-gu, Seoul",
    "district_en": "Jung-gu",
    "cuisine": "Various",
    "meal_times": [
      "Lunch",
      "Dinner"
    ],
    "description_en": "Restaurant of Chef Hu Deok-juk from Culinary Class Wars Season 2.",
    "lat": 37.5665,
    "lng": 126.978,
    "ccw_chef": "Hu Deok-juk"
  },
  {
    "id": "ccw_s2_w_22",
    "name_en": "Kojacha",
    "name": "Kojacha",
    "category_en": "Culinary Class Wars",
    "address": "Gangnam, Seoul",
    "district_en": "Gangnam",
    "cuisine": "Various",
    "meal_times": [
      "Lunch",
      "Dinner"
    ],
    "description_en": "Restaurant of Chef Choi Yu-gang from Culinary Class Wars Season 2.",
    "lat": 37.5665,
    "lng": 126.978,
    "ccw_chef": "Choi Yu-gang"
  },
  {
    "id": "ccw_s2_w_23",
    "name_en": "Soigné",
    "name": "Soigné",
    "category_en": "Culinary Class Wars",
    "address": "Gangnam, Seoul",
    "district_en": "Gangnam",
    "cuisine": "Various",
    "meal_times": [
      "Lunch",
      "Dinner"
    ],
    "description_en": "Restaurant of Chef Jun Lee from Culinary Class Wars Season 2.",
    "lat": 37.5665,
    "lng": 126.978,
    "ccw_chef": "Jun Lee"
  },
  {
    "id": "ccw_s2_w_24",
    "name_en": "Caden",
    "name": "Caden",
    "category_en": "Culinary Class Wars",
    "address": "Mapo, Seoul",
    "district_en": "Mapo",
    "cuisine": "Various",
    "meal_times": [
      "Lunch",
      "Dinner"
    ],
    "description_en": "Restaurant of Chef Jung Ho-young from Culinary Class Wars Season 2.",
    "lat": 37.5665,
    "lng": 126.978,
    "ccw_chef": "Jung Ho-young"
  },
  {
    "id": "ccw_s2_w_25",
    "name_en": "Suwon Galbi",
    "name": "Suwon Galbi",
    "category_en": "Culinary Class Wars",
    "address": "Suwon, Seoul",
    "district_en": "Suwon",
    "cuisine": "Various",
    "meal_times": [
      "Lunch",
      "Dinner"
    ],
    "description_en": "Restaurant of Chef Park Hyo-nam from Culinary Class Wars Season 2.",
    "lat": 37.5665,
    "lng": 126.978,
    "ccw_chef": "Park Hyo-nam"
  },
  {
    "id": "s_76",
    "name_en": "Halmeoni Kalguksu",
    "name": "찬양집",
    "category_en": "Kalguksu",
    "address": "5 Donhwamun-ro 11-gil, Jongno-gu",
    "district_en": "Jongno",
    "cuisine": "Korean",
    "meal_times": [
      "Lunch",
      "Dinner"
    ],
    "description_en": "Historic knife-cut noodle specialist in Ikseon-dong, famous for its rich seafood broth.",
    "lat": 37.5748,
    "lng": 126.9912,
    "michelin": "Bib Gourmand"
  },
  {
    "id": "s_77",
    "name_en": "Daeseong Jip",
    "name": "대성집",
    "category_en": "Dogani-tang",
    "address": "454 Tongil-ro, Jongno-gu",
    "district_en": "Jongno",
    "cuisine": "Korean",
    "meal_times": [
      "Breakfast",
      "Lunch",
      "Dinner"
    ],
    "description_en": "Famous for its ox knee soup (dogani-tang), a soulful and traditional Seoul dish.",
    "lat": 37.5725,
    "lng": 126.9605,
    "michelin": "Bib Gourmand"
  },
  {
    "id": "s_79",
    "name_en": "Manjok Ohyang Jokbal",
    "name": "만족 오향족발",
    "address": "134-7 Seosomun-ro, Jung-gu",
    "district_en": "Jung-gu",
    "cuisine": "Korean",
    "meal_times": [
      "Lunch",
      "Dinner"
    ],
    "description_en": "Award-winning braised pig's trotters with a unique five-spice aroma.",
    "lat": 37.5632,
    "lng": 126.9755,
    "michelin": "Bib Gourmand"
  },
  {
    "id": "s_81",
    "name_en": "Mapo Ok",
    "name": "마포옥",
    "category_en": "Seolleongtang",
    "address": "312-45 Yonggang-dong, Mapo-gu",
    "district_en": "Mapo",
    "cuisine": "Korean",
    "meal_times": [
      "Breakfast",
      "Lunch",
      "Dinner"
    ],
    "description_en": "Famous for its premium brisket beef soup, a local staple in Mapo since 1949.",
    "lat": 37.5405,
    "lng": 126.9415,
    "michelin": "Bib Gourmand"
  },
  {
    "id": "s_82",
    "name_en": "O'Hwaedang",
    "name": "오회당",
    "category_en": "Japanese Contemporary",
    "address": "12-3 Eonju-ro 164-gil, Gangnam-gu",
    "district_en": "Gangnam",
    "cuisine": "Japanese",
    "meal_times": [
      "Lunch",
      "Dinner"
    ],
    "description_en": "Refined Japanese contemporary dining focusing on seasonal seafood excellence.",
    "lat": 37.5255,
    "lng": 127.0365,
    "ribbons": 2
  },
  {
    "id": "s_83",
    "name_en": "Gwangjang Market Gohyang Kalguksu",
    "name": "고향칼국수",
    "category_en": "Kalguksu",
    "address": "88 Changgyeonggung-ro, Jongno-gu",
    "district_en": "Jongno",
    "cuisine": "Korean",
    "meal_times": [
      "Lunch",
      "Dinner"
    ],
    "description_en": "Featured on Netflix, this stall in Gwangjang Market is famous for its handmade noodles.",
    "lat": 37.5702,
    "lng": 126.9995,
    "ccw_chef": "Cho Yun-hee (Netflix)"
  },
  {
    "id": "s_84",
    "name_en": "Baek Je Yuk Hoe",
    "name": "백제육회",
    "category_en": "Yukhoe",
    "address": "210-1 Hyoje-dong, Jongno-gu",
    "district_en": "Jongno",
    "cuisine": "Korean",
    "meal_times": [
      "Lunch",
      "Dinner"
    ],
    "description_en": "Generous portions of fresh beef tartare, a favorite for local foodies in Jongno.",
    "lat": 37.5715,
    "lng": 127.0015
  },
  {
    "id": "s_86",
    "name_en": "Chungjin-ok",
    "name": "청진옥",
    "category_en": "Haejang-guk",
    "address": "32 Jong-ro 1-gil, Jongno-gu",
    "district_en": "Jongno",
    "cuisine": "Korean",
    "meal_times": [
      "Breakfast",
      "Lunch",
      "Dinner"
    ],
    "description_en": "The original hangover soup restaurant in Seoul, serving Jongno since 1937.",
    "lat": 37.5718,
    "lng": 126.9792
  },
  {
    "id": "s_87",
    "name_en": "Hwanggeum Kongbat",
    "name": "황금콩밭",
    "category_en": "Dubu",
    "address": "9 Mapo-daero 16-gil, Mapo-gu",
    "district_en": "Mapo",
    "cuisine": "Korean",
    "meal_times": [
      "Lunch",
      "Dinner"
    ],
    "description_en": "Specializes in artisanal handmade tofu, highlighting the pure taste of local beans.",
    "lat": 37.5495,
    "lng": 126.9545,
    "michelin": "Bib Gourmand"
  },
  {
    "id": "s_88",
    "name_en": "Yangmiok",
    "name": "양미옥",
    "category_en": "Daechang/Gopchang",
    "address": "62-11 Changgyeonggung-ro, Jung-gu",
    "district_en": "Jung-gu",
    "cuisine": "Korean",
    "meal_times": [
      "Lunch",
      "Dinner"
    ],
    "description_en": "Renowned for its grilled beef tripe and large intestines with a secret spicy marinade.",
    "lat": 37.5668,
    "lng": 126.9935
  },
  {
    "id": "s_89",
    "name_en": "Jinju Hoegwan",
    "name": "진주회관",
    "category_en": "Kong-guksu",
    "address": "26 Seosomun-ro 11-gil, Jung-gu",
    "district_en": "Jung-gu",
    "cuisine": "Korean",
    "meal_times": [
      "Lunch",
      "Dinner"
    ],
    "description_en": "Famous for its incredibly thick and creamy cold soy milk noodles (kong-guksu).",
    "lat": 37.5628,
    "lng": 126.9745
  },
  {
    "id": "s_90",
    "name_en": "Cheongmirae",
    "name": "청미래",
    "category_en": "Korean Traditional",
    "address": "25-10 Bangi-dong, Songpa-gu",
    "district_en": "Songpa",
    "cuisine": "Korean",
    "meal_times": [
      "Lunch",
      "Dinner"
    ],
    "description_en": "Traditional Korean dining focusing on health-conscious, chemical-free ingredients.",
    "lat": 37.5145,
    "lng": 127.1105
  },
  {
    "id": "s_91",
    "name_en": "Sanchon",
    "name": "산촌",
    "category_en": "Temple Food",
    "address": "30-13 Gwanhun-dong, Jongno-gu",
    "district_en": "Jongno",
    "cuisine": "Korean",
    "meal_times": [
      "Lunch",
      "Dinner"
    ],
    "description_en": "Authentic Buddhist temple cuisine served in a beautiful traditional hanok setting.",
    "lat": 37.5742,
    "lng": 126.9845
  },
  {
    "id": "s_92",
    "name_en": "Gaehwa-ok",
    "name": "개화옥",
    "category_en": "Korean Traditional",
    "address": "21 Dosan-daero 81-gil, Gangnam-gu",
    "district_en": "Gangnam",
    "cuisine": "Korean",
    "meal_times": [
      "Lunch",
      "Dinner"
    ],
    "description_en": "Modernized traditional Korean cuisine with a focus on seasonal beef and noodles.",
    "lat": 37.5265,
    "lng": 127.0445
  },
  {
    "id": "s_93",
    "name_en": "Kkujun",
    "name": "꾸준",
    "category_en": "Yakitori",
    "address": "12-14 Hannam-daero 20-gil, Yongsan-gu",
    "district_en": "Yongsan",
    "cuisine": "Japanese",
    "meal_times": [
      "Dinner"
    ],
    "description_en": "Specialized yakitori bar in Hannam-dong offering premium grilled chicken skewers.",
    "lat": 37.5348,
    "lng": 127.0092
  },
  {
    "id": "s_94",
    "name_en": "Fuchai",
    "name": "푸차이",
    "category_en": "Chinese",
    "address": "24 Teheran-ro 87-gil, Gangnam-gu",
    "district_en": "Gangnam",
    "cuisine": "Chinese",
    "meal_times": [
      "Lunch",
      "Dinner"
    ],
    "description_en": "High-end Chinese dining in Samseong-dong, known for its elegant course menus.",
    "lat": 37.5105,
    "lng": 127.0585
  },
  {
    "id": "s_95",
    "name_en": "Hwang Saeng Ga Kalguksu",
    "name": "황생가칼국수",
    "category_en": "Kalguksu",
    "address": "84 Bukchon-ro 5-gil, Jongno-gu",
    "district_en": "Jongno",
    "cuisine": "Korean",
    "meal_times": [
      "Lunch",
      "Dinner"
    ],
    "description_en": "Michelin-recognized kalguksu and mandu (dumplings) in the heart of Bukchon.",
    "lat": 37.5805,
    "lng": 126.9815,
    "michelin": "Bib Gourmand"
  },
  {
    "id": "s_96",
    "name_en": "Goyeo",
    "name": "고여",
    "category_en": "Korean Contemporary",
    "address": "2F, 31 Dosan-daero 45-gil, Gangnam-gu",
    "district_en": "Gangnam",
    "cuisine": "Korean",
    "meal_times": [
      "Lunch",
      "Dinner"
    ],
    "description_en": "A creative Korean dining experience that blends local ingredients with modern flair.",
    "lat": 37.5238,
    "lng": 127.0382
  },
  {
    "id": "s_97",
    "name_en": "Butanchu",
    "name": "부탄츄",
    "category_en": "Ramen",
    "address": "357-1 Seogyo-dong, Mapo-gu",
    "district_en": "Mapo",
    "cuisine": "Japanese",
    "meal_times": [
      "Lunch",
      "Dinner"
    ],
    "description_en": "One of the most popular tonkotsu ramen spots in Hongdae, famous for its rich broth.",
    "lat": 37.5555,
    "lng": 126.9235
  },
  {
    "id": "s_98",
    "name_en": "Hanoe",
    "name": "한외",
    "category_en": "Korean Traditional",
    "address": "15 Jong-ro 19-gil, Jongno-gu",
    "district_en": "Jongno",
    "cuisine": "Korean",
    "meal_times": [
      "Lunch",
      "Dinner"
    ],
    "description_en": "Specializes in traditional Korean beef dishes and home-style side dishes.",
    "lat": 37.5708,
    "lng": 126.9915
  },
  {
    "id": "s_99",
    "name_en": "Cheongmyeong",
    "name": "청명",
    "category_en": "Contemporary",
    "address": "14 Dosan-daero 15-gil, Gangnam-gu",
    "district_en": "Gangnam",
    "cuisine": "Contemporary",
    "meal_times": [
      "Lunch",
      "Dinner"
    ],
    "description_en": "Modern dining focusing on the harmony of global flavors and Korean seasonal produce.",
    "lat": 37.5195,
    "lng": 127.0225
  }
]